{
    "batches_completed": [
        "batch_07"
    ],
    "batches_blocked": [],
    "months_processed": [
        {
            "month": "2016-04",
            "sample": 19,
            "PF_base": 1.26,
            "expectancy_base": 0.1368,
            "total_R_base": 2.6,
            "PF_net_FTMO": 1.19,
            "expectancy_net_FTMO": 0.1005,
            "total_R_net_FTMO": 1.91,
            "avg_commission_R": 0.0364,
            "verdict_net_FTMO": "NET_FTMO_FRAGILE",
            "batch_id": "batch_07",
            "completed_at": "2026-05-03T19:31:10.858736"
        },
        {
            "month": "2016-05",
            "sample": 22,
            "PF_base": 2.02,
            "expectancy_base": 0.4182,
            "total_R_base": 9.2,
            "PF_net_FTMO": 1.85,
            "expectancy_net_FTMO": 0.3632,
            "total_R_net_FTMO": 7.99,
            "avg_commission_R": 0.055,
            "verdict_net_FTMO": "NET_FTMO_STRONG",
            "batch_id": "batch_07",
            "completed_at": "2026-05-03T19:34:40.315223"
        }
    ]
}