{
  "avg_trades_per_month": 0.23333333333333334,
  "break_even_setting": null,
  "breakeven_rate": 0.0,
  "costs_used": {},
  "expectancy_r": -0.17764200128343782,
  "insufficient_sample": true,
  "max_drawdown_pct": 3.8342166836126568,
  "negative_months": 1,
  "negative_years": 1,
  "news_filter_used": false,
  "parameter_set_used": {
    "adx_max": 22.0,
    "atr_period": 14,
    "deviation_sd": 1.8,
    "ema_period": 20,
    "ema_slope_atr_max": 0.45,
    "ema_slope_bars": 10,
    "max_target_rr": 1.5,
    "min_anchor_bars": 25,
    "session_end": "19:00",
    "session_name": "all_day",
    "session_start": "07:00",
    "stop_atr_buffer": 0.35
  },
  "positive_years": 0,
  "profit_factor": 0.653379491385636,
  "sample_penalty_applied": true,
  "schedule_used": {},
  "selected_score": null,
  "strategy_name": "mr01_anchor_elastic",
  "timeframe": "M15",
  "total_return_pct": -2.8656068624560826,
  "total_trades": 28,
  "win_rate": 50.0,
  "years_positive": 0
}